copulae/__init__.py
copulae/types.py
copulae/archimedean/__init__.py
copulae/archimedean/_shared.py
copulae/archimedean/abstract.py
copulae/archimedean/auxiliary.py
copulae/archimedean/clayton.py
copulae/archimedean/frank.py
copulae/archimedean/gumbel.py
copulae/copula/__init__.py
copulae/copula/base.py
copulae/copula/exceptions.py
copulae/copula/summary.py
copulae/copula/estimator/__init__.py
copulae/copula/estimator/corr_inversion.py
copulae/copula/estimator/estimator.py
copulae/copula/estimator/max_likelihood.py
copulae/copula/estimator/misc.py
copulae/copula/estimator/summary.py
copulae/core/__init__.py
copulae/core/exceptions.py
copulae/core/linalg.py
copulae/core/misc.py
copulae/datasets/__init__.py
copulae/datasets/base.py
copulae/datasets/data/danube.csv
copulae/datasets/data/marginal-data.csv
copulae/datasets/data/residuals.csv
copulae/datasets/data/smi.csv
copulae/elliptical/__init__.py
copulae/elliptical/abstract.py
copulae/elliptical/gaussian.py
copulae/elliptical/student.py
copulae/empirical/__init__.py
copulae/empirical/_distribution.c
copulae/empirical/_distribution.cp312-win_amd64.pyd
copulae/empirical/_distribution.pyx
copulae/empirical/distribution.py
copulae/empirical/empirical.py
copulae/empirical/summary.py
copulae/gof/__init__.py
copulae/gof/_exchangeability.c
copulae/gof/_exchangeability.cp312-win_amd64.pyd
copulae/gof/_exchangeability.pyx
copulae/gof/_radial_symmetry.c
copulae/gof/_radial_symmetry.cp312-win_amd64.pyd
copulae/gof/_radial_symmetry.pyx
copulae/gof/common.py
copulae/gof/exchangeability.py
copulae/gof/radial_symmetry.py
copulae/gof/goodness_of_fit/__init__.py
copulae/gof/goodness_of_fit/goodness_of_fit.py
copulae/gof/goodness_of_fit/utils.py
copulae/indep/__init__.py
copulae/indep/indep.py
copulae/indep/summary.py
copulae/marginal/__init__.py
copulae/marginal/marginal.py
copulae/marginal/summary.py
copulae/marginal/univariate.py
copulae/mixtures/__init__.py
copulae/mixtures/gmc/__init__.py
copulae/mixtures/gmc/exception.py
copulae-0.8.0.dist-info/LICENSE
copulae-0.8.0.dist-info/METADATA
copulae-0.8.0.dist-info/WHEEL
copulae-0.8.0.dist-info/top_level.txt
copulae-0.8.0.dist-info/RECORD
