Metadata-Version: 2.2
Name: copulae
Version: 0.8.0
Summary: Python copulae library for dependency modelling
Author-email: Daniel Bok <daniel.bok@outlook.com>
Maintainer-email: Daniel Bok <daniel.bok@outlook.com>
License: Copyright 2019 Daniel Bok
Project-URL: Documentation, https://copulae.readthedocs.io/en/latest/
Project-URL: Code, https://github.com/DanielBok/copulae
Project-URL: Issue tracker, https://github.com/DanielBok/copulae/issues
Keywords: copula,copulae,dependency modelling,dependence structures,archimdean,elliptical,finance
Classifier: Development Status :: 4 - Beta
Classifier: Intended Audience :: End Users/Desktop
Classifier: Intended Audience :: Financial and Insurance Industry
Classifier: Programming Language :: Python :: 3
Classifier: Programming Language :: Python :: 3.10
Classifier: Programming Language :: Python :: 3.11
Classifier: Programming Language :: Python :: 3.12
Classifier: Programming Language :: Python :: 3.13
Classifier: License :: OSI Approved :: MIT License
Classifier: Operating System :: MacOS :: MacOS X
Classifier: Operating System :: Microsoft :: Windows
Classifier: Operating System :: POSIX
Classifier: Programming Language :: Python
Classifier: Topic :: Scientific/Engineering
Requires-Python: >=3.10
License-File: LICENSE
Requires-Dist: numpy<3.0.0,>=2.0
Requires-Dist: pandas<3.0.0,>=2.1.4
Requires-Dist: scikit-learn<2.0.0,>=1.5.0
Requires-Dist: scipy<2.0.0,>=1.14.0
Requires-Dist: statsmodels<1.0.0,>=0.14.4
Requires-Dist: typing-extensions>=4.0.0; python_version < "3.11"
Requires-Dist: wrapt<2.0.0,>=1.14.0
